dbgpt/__init__.py
dbgpt/_version.py
dbgpt/component.py
dbgpt/_private/__init__.py
dbgpt/_private/config.py
dbgpt/_private/llm_metadata.py
dbgpt/_private/pydantic.py
dbgpt/agent/__init__.py
dbgpt/agent/core/__init__.py
dbgpt/agent/core/agent.py
dbgpt/agent/core/agent_manage.py
dbgpt/agent/core/base_agent.py
dbgpt/agent/core/base_team.py
dbgpt/agent/core/role.py
dbgpt/agent/core/schema.py
dbgpt/agent/core/user_proxy_agent.py
dbgpt/agent/core/action/__init__.py
dbgpt/agent/core/action/base.py
dbgpt/agent/core/action/blank_action.py
dbgpt/agent/core/memory/__init__.py
dbgpt/agent/core/memory/agent_memory.py
dbgpt/agent/core/memory/base.py
dbgpt/agent/core/memory/hybrid.py
dbgpt/agent/core/memory/llm.py
dbgpt/agent/core/memory/long_term.py
dbgpt/agent/core/memory/short_term.py
dbgpt/agent/core/memory/gpts/__init__.py
dbgpt/agent/core/memory/gpts/base.py
dbgpt/agent/core/memory/gpts/default_gpts_memory.py
dbgpt/agent/core/memory/gpts/gpts_memory.py
dbgpt/agent/core/plan/__init__.py
dbgpt/agent/core/plan/plan_action.py
dbgpt/agent/core/plan/planner_agent.py
dbgpt/agent/core/plan/team_auto_plan.py
dbgpt/agent/core/plan/awel/__init__.py
dbgpt/agent/core/plan/awel/agent_operator.py
dbgpt/agent/core/plan/awel/agent_operator_resource.py
dbgpt/agent/core/plan/awel/team_awel_layout.py
dbgpt/agent/core/profile/__init__.py
dbgpt/agent/core/profile/base.py
dbgpt/agent/expand/Indicator_assistant_agent.py
dbgpt/agent/expand/__init__.py
dbgpt/agent/expand/code_assistant_agent.py
dbgpt/agent/expand/dashboard_assistant_agent.py
dbgpt/agent/expand/data_scientist_agent.py
dbgpt/agent/expand/react_agent.py
dbgpt/agent/expand/simple_assistant_agent.py
dbgpt/agent/expand/summary_assistant_agent.py
dbgpt/agent/expand/tool_assistant_agent.py
dbgpt/agent/expand/actions/__init__.py
dbgpt/agent/expand/actions/chart_action.py
dbgpt/agent/expand/actions/code_action.py
dbgpt/agent/expand/actions/dashboard_action.py
dbgpt/agent/expand/actions/indicator_action.py
dbgpt-0.7.4.dist-info/METADATA
dbgpt-0.7.4.dist-info/WHEEL
dbgpt-0.7.4.dist-info/entry_points.txt
dbgpt-0.7.4.dist-info/RECORD
